LICENSE
code_commenter/__init__.py
code_commenter/cli.py
code_commenter-1.0.0.dist-info/entry_points.txt
code_commenter-1.0.0.dist-info/LICENSE
code_commenter-1.0.0.dist-info/WHEEL
code_commenter-1.0.0.dist-info/METADATA
code_commenter-1.0.0.dist-info/RECORD
