Metadata-Version: 2.1
Name: code-commenter
Version: 1.0.0
Summary: Lightweight tool to generate decorative code comments to enhance readability
License: MIT
Author: Tristan Naidoo
Requires-Python: >=3.7,<4.0
Classifier: License :: OSI Approved :: MIT License
Classifier: Programming Language :: Python :: 3
Classifier: Programming Language :: Python :: 3.7
Classifier: Programming Language :: Python :: 3.8
Classifier: Programming Language :: Python :: 3.9
Classifier: Programming Language :: Python :: 3.10
Classifier: Programming Language :: Python :: 3.11
Requires-Dist: pyperclip (>=1.8.2,<2.0.0)
